serverlessdl/__init__.py
serverlessdl/dataset.py
serverlessdl/exceptions.py
serverlessdl/network.py
serverlessdl/util.py
serverlessdl-1.0.4.dist-info/LICENSE
serverlessdl-1.0.4.dist-info/METADATA
serverlessdl-1.0.4.dist-info/WHEEL
serverlessdl-1.0.4.dist-info/top_level.txt
serverlessdl-1.0.4.dist-info/RECORD
