Metadata-Version: 2.1
Name: serverlessdl
Version: 1.0.4
Summary: Python tools for training Neural Networks in a serverless setup
Home-page: UNKNOWN
Author: Ning Wang
Author-email: nwang@futurewei.com
License: MIT
Platform: UNKNOWN
License-File: LICENSE
Requires-Dist: torch (>=1.7)
Requires-Dist: redisai (>=1.0.1)
Requires-Dist: pymongo (>=3.11.1)
Requires-Dist: flask (>=1.1.2)
